peakrdl_etana/__about__.py
peakrdl_etana/__init__.py
peakrdl_etana/__peakrdl__.py
peakrdl_etana/addr_decode.py
peakrdl_etana/dereferencer.py
peakrdl_etana/entry_points.py
peakrdl_etana/exporter.py
peakrdl_etana/external_acks.py
peakrdl_etana/forloop_generator.py
peakrdl_etana/hwif_report_generator.py
peakrdl_etana/identifier_filter.py
peakrdl_etana/module_tmpl.sv
peakrdl_etana/package_tmpl.sv
peakrdl_etana/parity.py
peakrdl_etana/scan_design.py
peakrdl_etana/sv_int.py
peakrdl_etana/template_generator.py
peakrdl_etana/utils.py
peakrdl_etana/validate_design.py
peakrdl_etana/cpuif/__init__.py
peakrdl_etana/cpuif/base.py
peakrdl_etana/cpuif/ahb/__init__.py
peakrdl_etana/cpuif/ahb/ahb_tmpl.sv
peakrdl_etana/cpuif/apb3/__init__.py
peakrdl_etana/cpuif/apb3/apb3_tmpl.sv
peakrdl_etana/cpuif/apb4/__init__.py
peakrdl_etana/cpuif/apb4/apb4_tmpl.sv
peakrdl_etana/cpuif/avalon/__init__.py
peakrdl_etana/cpuif/avalon/avalon_tmpl.sv
peakrdl_etana/cpuif/axi4lite/__init__.py
peakrdl_etana/cpuif/axi4lite/axi4lite_tmpl.sv
peakrdl_etana/cpuif/obi/__init__.py
peakrdl_etana/cpuif/obi/obi_tmpl.sv
peakrdl_etana/cpuif/passthrough/__init__.py
peakrdl_etana/cpuif/passthrough/passthrough_tmpl.sv
peakrdl_etana/field_logic/__init__.py
peakrdl_etana/field_logic/bases.py
peakrdl_etana/field_logic/generators.py
peakrdl_etana/field_logic/hw_interrupts.py
peakrdl_etana/field_logic/hw_interrupts_with_write.py
peakrdl_etana/field_logic/hw_set_clr.py
peakrdl_etana/field_logic/hw_write.py
peakrdl_etana/field_logic/sw_onread.py
peakrdl_etana/field_logic/sw_onwrite.py
peakrdl_etana/field_logic/sw_singlepulse.py
peakrdl_etana/field_logic/wide_field.py
peakrdl_etana/field_logic/templates/counter_macros.sv
peakrdl_etana/field_logic/templates/external_block.sv
peakrdl_etana/field_logic/templates/external_reg.sv
peakrdl_etana/field_logic/templates/field_storage.sv
peakrdl_etana/field_logic/templates/field_storage_sig.sv
peakrdl_etana/hwif/__init__.py
peakrdl_etana/hwif/generators.py
peakrdl_etana-0.7.0.dist-info/licenses/LICENSE
peakrdl_etana-0.7.0.dist-info/METADATA
peakrdl_etana-0.7.0.dist-info/WHEEL
peakrdl_etana-0.7.0.dist-info/entry_points.txt
peakrdl_etana-0.7.0.dist-info/top_level.txt
peakrdl_etana-0.7.0.dist-info/RECORD
