Metadata-Version: 2.4
Name: peakrdl-etana
Version: 0.7.0
Summary: Compile SystemRDL into a Verilog control/status register (CSR) block
Author: Dave Keeshan
License: LGPLv3
Project-URL: Source, https://github.com/daxzio/PeakRDL-etana
Project-URL: Tracker, https://github.com/daxzio/PeakRDL-etana/issues
Project-URL: Changelog, https://github.com/daxzio/PeakRDL-etana/releases
Project-URL: Documentation, https://peakrdl-etana.readthedocs.io/
Keywords: SystemRDL,PeakRDL,CSR,compiler,tool,registers,generator,Verilog,SystemVerilog,register abstraction layer,FPGA,ASIC
Classifier: Development Status :: 4 - Beta
Classifier: Programming Language :: Python
Classifier: Programming Language :: Python :: 3
Classifier: Programming Language :: Python :: 3.8
Classifier: Programming Language :: Python :: 3.9
Classifier: Programming Language :: Python :: 3.10
Classifier: Programming Language :: Python :: 3.11
Classifier: Programming Language :: Python :: 3.12
Classifier: Programming Language :: Python :: 3.13
Classifier: Programming Language :: Python :: 3 :: Only
Classifier: Intended Audience :: Developers
Classifier: License :: OSI Approved :: GNU Lesser General Public License v3 (LGPLv3)
Classifier: Operating System :: OS Independent
Classifier: Topic :: Scientific/Engineering :: Electronic Design Automation (EDA)
Requires-Python: >=3.8
License-File: LICENSE
Requires-Dist: peakrdl
Requires-Dist: systemrdl-compiler~=1.31
Requires-Dist: Jinja2>=2.11
Provides-Extra: cli
Requires-Dist: peakrdl-cli>=1.2.3; extra == "cli"
Dynamic: license-file
